profile_facebook_selenium_scraper_imp_local/__init__.py
profile_facebook_selenium_scraper_imp_local/facebook_constants.py
profile_facebook_selenium_scraper_imp_local/facebook_scraper.py
profile_facebook_selenium_scraper_imp_local-0.0.12.dist-info/METADATA
profile_facebook_selenium_scraper_imp_local-0.0.12.dist-info/WHEEL
profile_facebook_selenium_scraper_imp_local-0.0.12.dist-info/top_level.txt
profile_facebook_selenium_scraper_imp_local-0.0.12.dist-info/RECORD
