Metadata-Version: 2.1
Name: profile-facebook-selenium-scraper-imp-local
Version: 0.0.12
Summary: PyPI Package for Circles profile-facebook-selenium-scraper-imp-local Python
Home-page: https://github.com/circles-zone/profile-facebook-selenium-scraper-imp-local-python-package
Author: Circles
Author-email: info@circlez.ai
Classifier: Programming Language :: Python :: 3
Classifier: License :: Other/Proprietary License
Classifier: Operating System :: OS Independent
Requires-Dist: selenium >=4.20.0
Requires-Dist: logger-local >=0.0.135
Requires-Dist: profile-local >=0.0.65
Requires-Dist: language-remote >=0.0.20
Requires-Dist: python-sdk-remote >=0.0.75
